django_wm-4.2.0.dist-info/licenses/LICENSE
mentions/__init__.py
mentions/admin.py
mentions/apps.py
mentions/config.py
mentions/context_processors.py
mentions/contract.py
mentions/exceptions.py
mentions/microformats.py
mentions/options.py
mentions/permissions.py
mentions/py.typed
mentions/resolution.py
mentions/urls.py
mentions/forms/__init__.py
mentions/forms/submit_webmention.py
mentions/helpers/__init__.py
mentions/helpers/resolution.py
mentions/helpers/types.py
mentions/helpers/urls.py
mentions/helpers/util.py
mentions/helpers/thirdparty/__init__.py
mentions/helpers/thirdparty/wagtail/__init__.py
mentions/helpers/thirdparty/wagtail/proxy.py
mentions/helpers/thirdparty/wagtail/resolution.py
mentions/helpers/thirdparty/wagtail/urls.py
mentions/helpers/thirdparty/wagtail/util.py
mentions/management/__init__.py
mentions/management/commands/__init__.py
mentions/management/commands/mentions_pending.py
mentions/management/commands/mentions_reverify.py
mentions/management/commands/pending_mentions.py
mentions/middleware/__init__.py
mentions/middleware/webmention_head_middleware.py
mentions/migrations/0001_initial.py
mentions/migrations/0002_pendingincomingwebmention_pendingoutgoingcontent.py
mentions/migrations/0003_alter_simplemention_published_and_more.py
mentions/migrations/0004_simplemention_post_type_webmention_post_type_and_more.py
mentions/migrations/0005_rebuild_pending_models_with_constraints.py
mentions/migrations/0006_add_retryablemixin_pendingincomingwebmention_outgoingwebmentionstatus.py
mentions/migrations/0007_dashboardpermissionproxy.py
mentions/migrations/0008_alter_webmention_options.py
mentions/migrations/0009_alter_outgoingwebmentionstatus_options.py
mentions/migrations/0010_alter_hcard_avatar_alter_hcard_name.py
mentions/migrations/0011_alter_pendingoutgoingcontent_text.py
mentions/migrations/0012_alter_hcard_options_and_more.py
mentions/migrations/0013_webmention_has_been_read.py
mentions/migrations/0014_increase_urlfield_max_length.py
mentions/migrations/__init__.py
django_wm-4.2.0.dist-info/METADATA
django_wm-4.2.0.dist-info/WHEEL
django_wm-4.2.0.dist-info/top_level.txt
django_wm-4.2.0.dist-info/RECORD
