Metadata-Version: 2.4
Name: django-wm
Version: 4.2.0
Summary: Webmention support for Django.
Home-page: https://beatonma.org/webmentions_tester/
Author: Michael Beaton
Author-email: michael@beatonma.org
License: GPLv3
Project-URL: Source, https://github.com/beatonma/django-wm
Classifier: Framework :: Django
Classifier: Intended Audience :: Developers
Classifier: License :: OSI Approved :: GNU General Public License v3 (GPLv3)
Classifier: Programming Language :: Python :: 3.7
Classifier: Programming Language :: Python :: 3.8
Classifier: Programming Language :: Python :: 3.9
Classifier: Programming Language :: Python :: 3.10
Classifier: Programming Language :: Python :: 3.11
Classifier: Programming Language :: Python :: 3.12
Classifier: Programming Language :: Python :: 3.13
Requires-Python: >=3.7
License-File: LICENSE
Requires-Dist: beautifulsoup4>=4.6
Requires-Dist: Django>=2.2
Requires-Dist: mf2py>=1.1
Requires-Dist: requests>=2.20
Provides-Extra: celery
Requires-Dist: celery>=5.2.2; extra == "celery"
Provides-Extra: test
Requires-Dist: pytest; extra == "test"
Requires-Dist: pytest-django; extra == "test"
Provides-Extra: wagtail
Requires-Dist: wagtail>=3.0.3; extra == "wagtail"
Dynamic: license-file
